LICENSE
setup.cfg
setup.py
tellduslive
tellduslive.py
tellduslive.egg-info/PKG-INFO
tellduslive.egg-info/SOURCES.txt
tellduslive.egg-info/dependency_links.txt
tellduslive.egg-info/requires.txt
tellduslive.egg-info/top_level.txt