Metadata-Version: 2.1
Name: tellduslive
Version: 0.10.12
Summary: Communicate with Telldus Live
Home-page: https://github.com/molobrakos/tellduslive
Author: Erik
Author-email: error.errorsson@gmail.com
Classifier: License :: OSI Approved :: The Unlicense (Unlicense)
Provides: tellduslive
License-File: LICENSE
Requires-Dist: requests
Requires-Dist: requests_oauthlib
Provides-Extra: console
Requires-Dist: docopt; extra == "console"
